README.rst
bootstrap.py
buildout.cfg
setup.cfg
setup.py
docs/HISTORY.txt
docs/INSTALL.txt
docs/LICENSE.GPL
docs/LICENSE.txt
transmogrify/__init__.py
transmogrify.htmlcontentextractor.egg-info/PKG-INFO
transmogrify.htmlcontentextractor.egg-info/SOURCES.txt
transmogrify.htmlcontentextractor.egg-info/dependency_links.txt
transmogrify.htmlcontentextractor.egg-info/entry_points.txt
transmogrify.htmlcontentextractor.egg-info/namespace_packages.txt
transmogrify.htmlcontentextractor.egg-info/not-zip-safe
transmogrify.htmlcontentextractor.egg-info/requires.txt
transmogrify.htmlcontentextractor.egg-info/top_level.txt
transmogrify/htmlcontentextractor/__init__.py
transmogrify/htmlcontentextractor/autofinder.py
transmogrify/htmlcontentextractor/configure.zcml
transmogrify/htmlcontentextractor/templatefinder.py
transmogrify/htmlcontentextractor/templatefinder.txt
transmogrify/htmlcontentextractor/tests.py
transmogrify/htmlcontentextractor/external/__init__.py
transmogrify/htmlcontentextractor/external/base.py
transmogrify/htmlcontentextractor/external/normalize.py
transmogrify/htmlcontentextractor/external/relative_url.py
transmogrify/htmlcontentextractor/external/webchecker.py
transmogrify/htmlcontentextractor/external/websucker.py
transmogrify/htmlcontentextractor/webstemmer/Makefile
transmogrify/htmlcontentextractor/webstemmer/README.txt
transmogrify/htmlcontentextractor/webstemmer/__init__.py
transmogrify/htmlcontentextractor/webstemmer/analyze.py
transmogrify/htmlcontentextractor/webstemmer/extract.py
transmogrify/htmlcontentextractor/webstemmer/gzipstream.py
transmogrify/htmlcontentextractor/webstemmer/html2txt.py
transmogrify/htmlcontentextractor/webstemmer/htmldom.py
transmogrify/htmlcontentextractor/webstemmer/htmlparser3.py
transmogrify/htmlcontentextractor/webstemmer/htmlutils.py
transmogrify/htmlcontentextractor/webstemmer/httplib.py
transmogrify/htmlcontentextractor/webstemmer/layoutils.py
transmogrify/htmlcontentextractor/webstemmer/perf.py
transmogrify/htmlcontentextractor/webstemmer/sgmlparser3.py
transmogrify/htmlcontentextractor/webstemmer/style.py
transmogrify/htmlcontentextractor/webstemmer/textcrawler.py
transmogrify/htmlcontentextractor/webstemmer/urldbutils.py
transmogrify/htmlcontentextractor/webstemmer/zipdb.py
transmogrify/htmlcontentextractor/webstemmer/docs/compare.png
transmogrify/htmlcontentextractor/webstemmer/docs/extract.png
transmogrify/htmlcontentextractor/webstemmer/docs/findpat.png
