Metadata-Version: 1.0
Name: transmogrify.htmlcontentextractor
Version: 1.0
Summary: This blueprint extracts out title, description and body from html either via xpath or by automatic cluster analysis
Home-page: http://github.com/djay/transmogrify.htmlcontentextractor
Author: Dylan Jay
Author-email: software@pretaweb.com
License: GPL
Keywords: transmogrifier blueprint funnelweb source plone import conversion microsoft office
Platform: UNKNOWN
Classifier: Programming Language :: Python
Classifier: Topic :: Software Development :: Libraries :: Python Modules
